mlgorithms/__init__.py
mlgorithms/ID3/ID3.py
mlgorithms/ID3/__init__.py
mlgorithms/knn/__init__.py
mlgorithms/knn/knn.py
mlgorithms/naive_bayes/__init__.py
mlgorithms/naive_bayes/naive_bayes.py
mlgorithms/neural_genetic/NGA.py
mlgorithms/neural_genetic/__init__.py
mlgorithms/neural_genetic/accuracy_compare.py
mlgorithms/neural_network/ANN.py
mlgorithms/neural_network/__init__.py
mlgorithms-0.0.6.dist-info/LICENSE
mlgorithms-0.0.6.dist-info/METADATA
mlgorithms-0.0.6.dist-info/WHEEL
mlgorithms-0.0.6.dist-info/top_level.txt
mlgorithms-0.0.6.dist-info/RECORD
