Metadata-Version: 2.1
Name: mlgorithms
Version: 0.0.6
Summary: Machine Learning Lib.
Home-page: https://github.com/doycode/mlgorithms.git
Author: Dong
Author-email: dongyuncheng1991@gmail.com
License: UNKNOWN
Platform: UNKNOWN
Classifier: Programming Language :: Python :: 3
Classifier: License :: OSI Approved :: Apache Software License
Classifier: Operating System :: OS Independent
Requires-Dist: matplotlib
Requires-Dist: numpy
Requires-Dist: scikit-learn
Requires-Dist: scipy
